[
  {
    "rank": "1",
    "pref": "長野県",
    "city": "開田高原",
    "temp": "14.5 )",
    "time": "05:04)",
    "memo": "",
    "code": "48531",
    "group": "長野県",
    "kana": "カイダコウゲン",
    "lat": 35.93833333,
    "lon": 137.6016667
  },
  {
    "rank": "2",
    "pref": "岩手県",
    "city": "区界",
    "temp": "14.7 )",
    "time": "02:49)",
    "memo": "",
    "code": "33441",
    "group": "岩手県",
    "kana": "クザカイ",
    "lat": 39.65,
    "lon": 141.3533333
  },
  {
    "rank": "3",
    "pref": "岐阜県",
    "city": "六厩",
    "temp": "15.0 )",
    "time": "04:33)",
    "memo": "",
    "code": "52181",
    "group": "岐阜県",
    "kana": "ムマヤ",
    "lat": 36.06,
    "lon": 137.035
  },
  {
    "rank": "4",
    "pref": "北海道 根室地方",
    "city": "納沙布",
    "temp": "15.4 )",
    "time": "01:45)",
    "memo": "",
    "code": "18281",
    "group": "北海道 根室地方",
    "kana": "ノサップ",
    "lat": 43.39333333,
    "lon": 145.7583333
  },
  {
    "rank": "5",
    "pref": "北海道 釧路地方",
    "city": "榊町",
    "temp": "15.7 )",
    "time": "07:41)",
    "memo": "",
    "code": "19311",
    "group": "北海道 釧路地方",
    "kana": "サカキマチ",
    "lat": 43.12,
    "lon": 145.11
  },
  {
    "rank": "5",
    "pref": "岩手県",
    "city": "薮川",
    "temp": "15.7 )",
    "time": "01:54)",
    "memo": "",
    "code": "33371",
    "group": "岩手県",
    "kana": "ヤブカワ",
    "lat": 39.78333333,
    "lon": 141.3283333
  },
  {
    "rank": "7",
    "pref": "長野県",
    "city": "奈川",
    "temp": "15.9 )",
    "time": "04:42)",
    "memo": "",
    "code": "48466",
    "group": "長野県",
    "kana": "ナガワ",
    "lat": 36.08833333,
    "lon": 137.6833333
  },
  {
    "rank": "7",
    "pref": "岐阜県",
    "city": "宮之前",
    "temp": "15.9 )",
    "time": "05:03)",
    "memo": "",
    "code": "52196",
    "group": "岐阜県",
    "kana": "ミヤノマエ",
    "lat": 36.015,
    "lon": 137.3883333
  },
  {
    "rank": "9",
    "pref": "北海道 根室地方",
    "city": "根室",
    "temp": "16.0 )",
    "time": "00:57)",
    "memo": "",
    "code": "18174",
    "group": "北海道 根室地方",
    "kana": "ネムロナカシベツ",
    "lat": 43.57666667,
    "lon": 144.96
  },
  {
    "rank": "10",
    "pref": "北海道 日高地方",
    "city": "えりも岬",
    "temp": "16.2 )",
    "time": "03:29)",
    "memo": "",
    "code": "22391",
    "group": "北海道 日高地方",
    "kana": "エリモミサキ",
    "lat": 41.925,
    "lon": 143.2433333
  }
]